LICENCE
README.md
setup.py
plataforma/__init__.py
plataforma/automaxia_api.py
plataforma_automaxia_api.egg-info/PKG-INFO
plataforma_automaxia_api.egg-info/SOURCES.txt
plataforma_automaxia_api.egg-info/dependency_links.txt
plataforma_automaxia_api.egg-info/requires.txt
plataforma_automaxia_api.egg-info/top_level.txt