Metadata-Version: 2.1
Name: plataforma-automaxia-api
Version: 0.0.10
Summary: Wrapper oficial da Plataforma Automaxia para Python
Home-page: UNKNOWN
Author: Wesley Romualdo da Silva
Author-email: wesleyromualdo@gmail.com
License: MIT License
Keywords: plataforma automaxia api
Platform: UNKNOWN
License-File: LICENCE
